LICENSE
MANIFEST.in
README.md
setup.cfg
setup.py
rtt_data_gen/__init__.py
rtt_data_gen/base.py
rtt_data_gen/errors.py
rtt_data_gen/main.py
rtt_data_gen/qrng.py
rtt_data_gen/spreader.py
rtt_data_gen/utils.py
rtt_data_gen/visualizer.py
rtt_data_gen.egg-info/PKG-INFO
rtt_data_gen.egg-info/SOURCES.txt
rtt_data_gen.egg-info/dependency_links.txt
rtt_data_gen.egg-info/entry_points.txt
rtt_data_gen.egg-info/requires.txt
rtt_data_gen.egg-info/top_level.txt
rtt_data_gen/tests/__init__.py
rtt_data_gen/tests/spreader_tests.py